simple_pyms-0.2.0.dist-info/METADATA
simple_pyms-0.2.0.dist-info/RECORD
simple_pyms-0.2.0.dist-info/WHEEL
simple_pyms-0.2.0.dist-info/top_level.txt
simplepyms/__init__.py
simplepyms/microservice.py
simplepyms/monitor.py
simplepyms/topics.py
