Metadata-Version: 2.1
Name: simple-pyms
Version: 0.2.0
Summary: Microservices Without Headaches
Home-page: UNKNOWN
Author: Jaime Wyant
Author-email: programmer.py@gmail.com
License: UNKNOWN
Platform: UNKNOWN
Requires-Dist: attrs (>=18.1.0)
Requires-Dist: autobahn (>=18.7.1)
Requires-Dist: automat (>=0.7.0)
Requires-Dist: constantly (>=15.1.0)
Requires-Dist: hyperlink (>=18.0.0)
Requires-Dist: idna (>=2.7)
Requires-Dist: incremental (>=17.5.0)
Requires-Dist: psutil (>=5.4.6)
Requires-Dist: pyhamcrest (>=1.9.0)
Requires-Dist: six (>=1.11.0)
Requires-Dist: twisted (>=18.7.0)
Requires-Dist: txaio (>=18.7.1)
Requires-Dist: zope.interface (>=4.5.0); python_version != "3.1.*"
Requires-Dist: pywin32 (>=223); sys_platform == "win32"
